github_webhooks/__init__.py
github_webhooks/apps.py
github_webhooks/constants.py
github_webhooks/settings.py
github_webhooks/signals.py
github_webhooks/urls.py
github_webhooks/utils.py
github_webhooks/views.py
django_github_webhooks-1.1.0.dist-info/LICENSE
django_github_webhooks-1.1.0.dist-info/WHEEL
django_github_webhooks-1.1.0.dist-info/METADATA
django_github_webhooks-1.1.0.dist-info/RECORD
