Metadata-Version: 2.1
Name: django-github-webhooks
Version: 1.1.0
Summary: GitHub webhooks for Django.
Home-page: https://github.com/OpenWiden/django-github-webhooks
License: MIT
Keywords: django,github,webhooks
Author: stefanitsky
Author-email: stefanitsky.mozdor@gmail.com
Requires-Python: >=3.6,<4.0
Classifier: Framework :: Django :: 2.1
Classifier: Framework :: Django :: 3.0
Classifier: License :: OSI Approved :: MIT License
Classifier: Operating System :: OS Independent
Classifier: Programming Language :: Python :: 3
Classifier: Programming Language :: Python :: 3.6
Classifier: Programming Language :: Python :: 3.7
Classifier: Programming Language :: Python :: 3.8
Provides-Extra: black
Provides-Extra: dev
Provides-Extra: docs
Provides-Extra: isort
Provides-Extra: test
Requires-Dist: black (>=19.10b0,<20.0); extra == "black" or extra == "dev"
Requires-Dist: django (>=2.2,<4.0)
Requires-Dist: isort[pyproject] (>=4.3.21,<5.0.0); extra == "isort" or extra == "dev"
Requires-Dist: pytest (>=5.2,<6.0); extra == "test" or extra == "dev"
Requires-Dist: pytest-cov (>=2.1.0,<3.0.0); extra == "test" or extra == "dev"
Requires-Dist: pytest-django (>=3.9.0,<4.0.0); extra == "test" or extra == "dev"
Requires-Dist: sphinx (>=3,<4); extra == "docs" or extra == "dev"
Requires-Dist: tox (<3.8); extra == "dev"
Project-URL: Documentation, https://django-github-webhooks.readthedocs.io/en/latest/
Project-URL: Repository, https://github.com/OpenWiden/django-github-webhooks
